documentation_generator/__init__.py
documentation_generator/document.py
documentation_generator/items.py
documentation_generator/main.py
documentation_generator/render.py
documentation_generator/assets/.placeholder
documentation_generator/assets/shadcdn.css
documentation_generator-0.1.0.dist-info/METADATA
documentation_generator-0.1.0.dist-info/WHEEL
documentation_generator-0.1.0.dist-info/entry_points.txt
documentation_generator-0.1.0.dist-info/RECORD
