Metadata-Version: 2.4
Name: documentation-generator
Version: 0.1.0
Summary: Add your description here
Requires-Python: >=3.13
Requires-Dist: markdown
Requires-Dist: tabulate
Requires-Dist: weasyprint>=66.0
Provides-Extra: dev
Requires-Dist: ipykernel; extra == 'dev'
Requires-Dist: pytest; extra == 'dev'
Provides-Extra: pdf
Requires-Dist: weasyprint; extra == 'pdf'
